phazap/__init__.py
phazap/_version.py
phazap/gw_utils.py
phazap/gwphase.py
phazap/pe_input.py
phazap/phazap.py
phazap/plot_utils.py
phazap/postprocess_phase.py
phazap/tension_utils.py
phazap/utils.py
phazap-0.3.3.dist-info/LICENSE
phazap-0.3.3.dist-info/METADATA
phazap-0.3.3.dist-info/WHEEL
phazap-0.3.3.dist-info/top_level.txt
phazap-0.3.3.dist-info/RECORD
