Metadata-Version: 2.1
Name: phazap
Version: 0.3.3
Summary: Gravitational wave phase reconstruction for low-latency identification of strongly lensed signals
Author: Jose María Ezquiaga
Author-email: jose.ezquiaga@nbi.ku.dk
Classifier: Programming Language :: Python :: 3.7
Requires-Python: >=3.7
License-File: LICENSE
Requires-Dist: bilby
Requires-Dist: bilby-pipe
Requires-Dist: pesummary
Requires-Dist: getdist
Requires-Dist: tqdm
Requires-Dist: configargparse
Requires-Dist: numpy >=1.21.0
